{
  "version": 1,
  "updatedAt": "2026-07-16T00:00:00.000Z",
  "topics": [
    { "id": "typography", "label": "Typography" },
    { "id": "motion", "label": "Motion" },
    { "id": "depth", "label": "Depth & Color" },
    { "id": "layout", "label": "Layout & Alignment" },
    { "id": "polish", "label": "Polish" }
  ],
  "sections": [
    {
      "id": "text-wrapping",
      "title": "Text wrapping",
      "topicId": "typography",
      "source": {
        "author": "Jakub Krehel",
        "article": "Details That Make Interfaces Feel Better",
        "url": "https://jakub.kr/writing/details-that-make-interfaces-feel-better"
      },
      "blocks": [
        {
          "id": "tw1",
          "type": "text",
          "text": "Browsers break lines greedily by default — they fill each line as far as it goes, which leaves headlines lopsided and paragraphs ending on a single orphaned word. Two CSS properties fix this for free: `text-wrap: balance` distributes a short run of text evenly across its lines (made for titles), and `text-wrap: pretty` avoids orphans at the end of longer paragraphs."
        },
        {
          "id": "tw2",
          "type": "demo",
          "demoId": "text-wrap",
          "caption": "Drag the width and switch modes — watch how the lines redistribute."
        },
        {
          "id": "tw3",
          "type": "code",
          "lang": "css",
          "code": "h1, h2, h3, blockquote {\n  text-wrap: balance; /* even lines for short runs */\n}\n\np {\n  text-wrap: pretty; /* no orphaned last words */\n}"
        },
        {
          "id": "tw4",
          "type": "callout",
          "style": "soft",
          "text": "Rule of thumb: **balance** for anything under ~4 lines, **pretty** for body copy. Both are progressive enhancements — old browsers simply ignore them."
        }
      ]
    },
    {
      "id": "crisp-text",
      "title": "Make text crisp",
      "topicId": "typography",
      "source": {
        "author": "Jakub Krehel",
        "article": "Details That Make Interfaces Feel Better",
        "url": "https://jakub.kr/writing/details-that-make-interfaces-feel-better"
      },
      "blocks": [
        {
          "id": "ct1",
          "type": "text",
          "text": "On macOS the default subpixel rendering makes text look slightly bolder and fuzzier than designed. Switching to grayscale antialiasing renders type thinner and crisper — closer to what you see in Figma. Apply it once, globally."
        },
        {
          "id": "ct2",
          "type": "demo",
          "demoId": "font-smoothing",
          "caption": "The difference is subtle at body sizes and obvious on light text over dark."
        },
        {
          "id": "ct3",
          "type": "code",
          "lang": "css",
          "code": "body {\n  -webkit-font-smoothing: antialiased;\n  text-rendering: optimizeLegibility;\n}"
        }
      ]
    },
    {
      "id": "tabular-numbers",
      "title": "Use tabular numbers",
      "topicId": "typography",
      "source": {
        "author": "Jakub Krehel",
        "article": "Details That Make Interfaces Feel Better",
        "url": "https://jakub.kr/writing/details-that-make-interfaces-feel-better"
      },
      "blocks": [
        {
          "id": "tn1",
          "type": "text",
          "text": "Most fonts give digits proportional widths — a 1 is narrower than an 8 — so any number that updates in place (timers, counters, prices) jitters sideways as it ticks. `font-variant-numeric: tabular-nums` makes every digit the same width, and the layout holds still."
        },
        {
          "id": "tn2",
          "type": "demo",
          "demoId": "tabular-nums",
          "caption": "Same timer, twice. Only one of them vibrates."
        },
        {
          "id": "tn3",
          "type": "code",
          "lang": "css",
          "code": ".timer, .counter, td.amount {\n  font-variant-numeric: tabular-nums;\n}"
        },
        {
          "id": "tn4",
          "type": "callout",
          "style": "soft",
          "text": "Check your typeface first — some fonts (Inter, for one) draw tabular digits differently enough that you'll want to compare before shipping."
        }
      ]
    },
    {
      "id": "icon-transitions",
      "title": "Animate icons contextually",
      "topicId": "motion",
      "source": {
        "author": "Jakub Krehel",
        "article": "Details That Make Interfaces Feel Better",
        "url": "https://jakub.kr/writing/details-that-make-interfaces-feel-better"
      },
      "blocks": [
        {
          "id": "it1",
          "type": "text",
          "text": "When an icon swaps to reflect state — copy turning into a checkmark — an instant swap reads as a glitch. Cross-fading the two icons with a touch of scale and blur makes the state change feel acknowledged rather than replaced."
        },
        {
          "id": "it2",
          "type": "demo",
          "demoId": "icon-swap",
          "caption": "Copy something. The left button swaps instantly; the right one transitions."
        },
        {
          "id": "it3",
          "type": "code",
          "lang": "css",
          "code": ".icon {\n  transition:\n    opacity 0.25s var(--ease),\n    transform 0.25s var(--ease),\n    filter 0.25s var(--ease);\n}\n.icon.leaving {\n  opacity: 0;\n  transform: scale(0.6);\n  filter: blur(3px);\n}"
        }
      ]
    },
    {
      "id": "interruptible-animations",
      "title": "Make animations interruptible",
      "topicId": "motion",
      "source": {
        "author": "Jakub Krehel",
        "article": "Details That Make Interfaces Feel Better",
        "url": "https://jakub.kr/writing/details-that-make-interfaces-feel-better"
      },
      "blocks": [
        {
          "id": "ia1",
          "type": "text",
          "text": "CSS transitions retarget mid-flight: change the destination while one is running and it glides toward the new value from wherever it is. Keyframe animations don't — they run their fixed timeline to the end, and re-triggering one snaps it back to frame zero. For anything the user can poke repeatedly, that difference is the difference between an interface that feels responsive and one that feels stuck."
        },
        {
          "id": "ia2",
          "type": "demo",
          "demoId": "interruptible",
          "caption": "Spam the toggle. The transition follows you; the keyframes ignore you."
        },
        {
          "id": "ia3",
          "type": "callout",
          "style": "highlight",
          "text": "Transitions for interactions, keyframes for one-off sequences (entrances, loaders). If a user can re-trigger it, it must be interruptible."
        }
      ]
    },
    {
      "id": "stagger-entrances",
      "title": "Split and stagger entrances",
      "topicId": "motion",
      "source": {
        "author": "Jakub Krehel",
        "article": "Details That Make Interfaces Feel Better",
        "url": "https://jakub.kr/writing/details-that-make-interfaces-feel-better"
      },
      "blocks": [
        {
          "id": "se1",
          "type": "text",
          "text": "Animating a whole page in as one block is heavy-handed. Split the content into pieces and let them enter a beat apart — opacity, a small translateY, a hint of blur — and the same entrance suddenly has rhythm. Delay each piece by ~80–100ms more than the last."
        },
        {
          "id": "se2",
          "type": "demo",
          "demoId": "stagger",
          "caption": "One entrance, three granularities. Replay each."
        },
        {
          "id": "se3",
          "type": "code",
          "lang": "css",
          "code": "@keyframes enter {\n  from {\n    opacity: 0;\n    transform: translateY(8px);\n    filter: blur(8px);\n  }\n}\n\n[data-animate] {\n  animation: enter 0.8s var(--ease) both;\n  animation-delay: calc(var(--stagger, 0) * 100ms);\n}"
        },
        {
          "id": "se4",
          "type": "callout",
          "style": "soft",
          "text": "Set `--stagger: 1..n` on successive elements. Keep the count modest — staggering forty list items keeps the user waiting for no reason."
        }
      ]
    },
    {
      "id": "subtle-exits",
      "title": "Make exit animations subtle",
      "topicId": "motion",
      "source": {
        "author": "Jakub Krehel",
        "article": "Details That Make Interfaces Feel Better",
        "url": "https://jakub.kr/writing/details-that-make-interfaces-feel-better"
      },
      "blocks": [
        {
          "id": "sx1",
          "type": "text",
          "text": "Entrances introduce something the user should notice; exits remove something they're already done with. Giving both the same weight makes leaving feel as loud as arriving. Let exits step back — a quick fade with a touch of blur — instead of sliding dramatically off-screen."
        },
        {
          "id": "sx2",
          "type": "demo",
          "demoId": "exit",
          "caption": "Dismiss items in both lists. The right one lets go quietly."
        },
        {
          "id": "sx3",
          "type": "code",
          "lang": "jsx",
          "code": "// loud: exit mirrors the entrance\nexit={{ x: \"calc(-100% - 4px)\" }}\n\n// quiet: exits demand less attention\nexit={{ opacity: 0, filter: \"blur(4px)\" }}"
        }
      ]
    },
    {
      "id": "concentric-radius",
      "title": "Concentric border radius",
      "topicId": "layout",
      "source": {
        "author": "Jakub Krehel",
        "article": "Details That Make Interfaces Feel Better",
        "url": "https://jakub.kr/writing/details-that-make-interfaces-feel-better"
      },
      "blocks": [
        {
          "id": "cr1",
          "type": "text",
          "text": "When a rounded element sits inside another rounded element, reusing the same radius makes the corners visually diverge — the gap between the two curves is thicker at the corner than along the edges. The fix is one formula: the outer radius should equal the inner radius plus the padding between them. Then the curves share a center and the spacing reads even all the way around."
        },
        {
          "id": "cr2",
          "type": "demo",
          "demoId": "concentric-radius",
          "caption": "Scrub the values. The naive version pinches at the corners."
        },
        {
          "id": "cr3",
          "type": "code",
          "lang": "css",
          "code": ".outer {\n  --pad: 8px;\n  --inner-r: 12px;\n  padding: var(--pad);\n  border-radius: calc(var(--inner-r) + var(--pad)); /* 20px */\n}\n.inner {\n  border-radius: var(--inner-r);\n}"
        }
      ]
    },
    {
      "id": "optical-alignment",
      "title": "Align optically, not geometrically",
      "topicId": "layout",
      "source": {
        "author": "Jakub Krehel",
        "article": "Details That Make Interfaces Feel Better",
        "url": "https://jakub.kr/writing/details-that-make-interfaces-feel-better"
      },
      "blocks": [
        {
          "id": "oa1",
          "type": "text",
          "text": "Perfectly centered is not always perceived as centered. A play triangle sitting mathematically in the middle of a circle looks like it's drifting left, because its visual mass sits toward its back edge. Asymmetric shapes need a nudge — a pixel or two of margin against the math — until they *look* right. Fixing it inside the SVG itself is cleanest, so every use of the icon inherits the correction."
        },
        {
          "id": "oa2",
          "type": "demo",
          "demoId": "optical",
          "caption": "Toggle the correction. Trust your eye, not the ruler."
        },
        {
          "id": "oa3",
          "type": "callout",
          "style": "soft",
          "text": "Same story for text next to icons, chevrons in buttons, and badges beside labels: when it looks off but measures fine, the measurement is what's wrong."
        }
      ]
    },
    {
      "id": "shadows-not-borders",
      "title": "Use shadows instead of borders",
      "topicId": "depth",
      "source": {
        "author": "Jakub Krehel",
        "article": "Details That Make Interfaces Feel Better",
        "url": "https://jakub.kr/writing/details-that-make-interfaces-feel-better"
      },
      "blocks": [
        {
          "id": "sb1",
          "type": "text",
          "text": "A 1px solid border is a flat, opaque line — it sits on top of whatever's behind it and always looks the same. A ring built from layered box-shadows is translucent: it picks up the background, so the same card works on white, on tint, on a pattern. Stack a hairline ring with one or two soft drops and you get an edge plus depth in a single declaration."
        },
        {
          "id": "sb2",
          "type": "demo",
          "demoId": "shadows",
          "caption": "Border vs shadow ring, on quiet and busy backgrounds. Hover the cards."
        },
        {
          "id": "sb3",
          "type": "code",
          "lang": "css",
          "code": ".card {\n  box-shadow:\n    0 0 0 1px rgba(0, 0, 0, 0.06),\n    0 1px 2px -1px rgba(0, 0, 0, 0.06),\n    0 2px 4px 0 rgba(0, 0, 0, 0.04);\n  transition: box-shadow 0.3s var(--ease);\n}\n.card:hover {\n  box-shadow:\n    0 0 0 1px rgba(0, 0, 0, 0.08),\n    0 1px 2px -1px rgba(0, 0, 0, 0.08),\n    0 2px 4px 0 rgba(0, 0, 0, 0.06);\n}"
        }
      ]
    },
    {
      "id": "image-outlines",
      "title": "Add an outline to images",
      "topicId": "depth",
      "source": {
        "author": "Jakub Krehel",
        "article": "Details That Make Interfaces Feel Better",
        "url": "https://jakub.kr/writing/details-that-make-interfaces-feel-better"
      },
      "blocks": [
        {
          "id": "io1",
          "type": "text",
          "text": "Photos with light edges — skies, white studio backgrounds — bleed into a light page and look like they're floating unbounded. A 1px inset outline at 10% black quietly contains every image, whatever its content, and disappears on images that never needed it."
        },
        {
          "id": "io2",
          "type": "demo",
          "demoId": "image-outline",
          "caption": "Toggle the outline. The light-edged image is the one it saves."
        },
        {
          "id": "io3",
          "type": "code",
          "lang": "css",
          "code": "img {\n  outline: 1px solid rgba(0, 0, 0, 0.1);\n  outline-offset: -1px; /* sits just inside the edge */\n}\n\n/* dark mode */\n.dark img {\n  outline-color: rgba(255, 255, 255, 0.1);\n}"
        }
      ]
    },
    {
      "id": "before-after",
      "title": "Before and after",
      "topicId": "polish",
      "source": {
        "author": "Jakub Krehel",
        "article": "Details That Make Interfaces Feel Better",
        "url": "https://jakub.kr/writing/details-that-make-interfaces-feel-better"
      },
      "blocks": [
        {
          "id": "ba1",
          "type": "text",
          "text": "None of these details matters much alone — each is a percent or two of polish. Applied together, the same component reads a class apart: balanced text, concentric corners, a shadow ring instead of a border, tabular digits in the timer, an icon that transitions when tapped, everything aligned to the eye."
        },
        {
          "id": "ba2",
          "type": "demo",
          "demoId": "before-after",
          "caption": "The same card with everything off, then everything on."
        },
        {
          "id": "ba3",
          "type": "callout",
          "style": "pull",
          "text": "Craft is cumulative. Users can't name a single one of these details — they just say the interface feels better."
        }
      ]
    }
  ]
}
